MANIFEST.in
README
README.md
setup.py
nanosql/__init__.py
nanosql/main.py
nanosql.egg-info/PKG-INFO
nanosql.egg-info/SOURCES.txt
nanosql.egg-info/dependency_links.txt
nanosql.egg-info/entry_points.txt
nanosql.egg-info/requires.txt
nanosql.egg-info/top_level.txt