Metadata-Version: 1.0
Name: nanosql
Version: 0.1.1
Summary: Edit a slice of a SQL database in nano
Home-page: https://github.com/paulfitz/nanosql
Author: Paul Fitzpatrick
Author-email: paulfitz@alum.mit.edu
License: UNKNOWN
Platform: UNKNOWN
